{
  "SPY daily": {
    "short tp1:1": {
      "gross": {
        "n": 58,
        "win": 0.43103448275862066,
        "meanR": -0.15365093718895215,
        "spt": -0.1568778219700094,
        "sumR": -8.911754356959225
      },
      "net": {
        "n": 58,
        "win": 0.43103448275862066,
        "meanR": -0.16850106372251974,
        "spt": -0.17232036257528252,
        "sumR": -9.773061695906145
      }
    },
    "short tp2:1": {
      "gross": {
        "n": 55,
        "win": 0.2727272727272727,
        "meanR": -0.20177459383608448,
        "spt": -0.1538719319272929,
        "sumR": -11.097602660984647
      },
      "net": {
        "n": 55,
        "win": 0.2727272727272727,
        "meanR": -0.2165677397719421,
        "spt": -0.16532897845344013,
        "sumR": -11.911225687456815
      }
    },
    "long tp1:1": {
      "gross": {
        "n": 65,
        "win": 0.5538461538461539,
        "meanR": 0.08679747848668136,
        "spt": 0.088257188943899,
        "sumR": 5.641836101634288
      },
      "net": {
        "n": 65,
        "win": 0.5538461538461539,
        "meanR": 0.06817618198176463,
        "spt": 0.06930605021056507,
        "sumR": 4.431451828814701
      }
    },
    "long tp2:1": {
      "gross": {
        "n": 61,
        "win": 0.4426229508196721,
        "meanR": 0.24508853123597032,
        "spt": 0.1712189419000476,
        "sumR": 14.95040040539419
      },
      "net": {
        "n": 61,
        "win": 0.4426229508196721,
        "meanR": 0.2264677401302109,
        "spt": 0.1580797093471236,
        "sumR": 13.814532147942865
      }
    }
  },
  "QQQ daily": {
    "short tp1:1": {
      "gross": {
        "n": 52,
        "win": 0.36538461538461536,
        "meanR": -0.28723392659870833,
        "spt": -0.30305003238092226,
        "sumR": -14.936164183132833
      },
      "net": {
        "n": 52,
        "win": 0.36538461538461536,
        "meanR": -0.29724817049853497,
        "spt": -0.3135935308947417,
        "sumR": -15.456904865923818
      }
    },
    "short tp2:1": {
      "gross": {
        "n": 50,
        "win": 0.22,
        "meanR": -0.39921486011114665,
        "spt": -0.3423569064180597,
        "sumR": -19.960743005557333
      },
      "net": {
        "n": 50,
        "win": 0.22,
        "meanR": -0.40936949729613387,
        "spt": -0.35083461913859015,
        "sumR": -20.468474864806694
      }
    },
    "long tp1:1": {
      "gross": {
        "n": 55,
        "win": 0.4909090909090909,
        "meanR": -0.03151079195000713,
        "spt": -0.031873900442608155,
        "sumR": -1.7330935572503923
      },
      "net": {
        "n": 55,
        "win": 0.4909090909090909,
        "meanR": -0.045594252473199794,
        "spt": -0.046146953379954336,
        "sumR": -2.5076838860259887
      }
    },
    "long tp2:1": {
      "gross": {
        "n": 55,
        "win": 0.41818181818181815,
        "meanR": 0.1721496707220357,
        "spt": 0.1226356826038413,
        "sumR": 9.468231889711964
      },
      "net": {
        "n": 55,
        "win": 0.41818181818181815,
        "meanR": 0.15806621019884304,
        "spt": 0.11262136959594857,
        "sumR": 8.693641560936367
      }
    }
  },
  "GLD daily": {
    "short tp1:1": {
      "gross": {
        "n": 32,
        "win": 0.46875,
        "meanR": -0.07763340282647346,
        "spt": -0.07878276269715787,
        "sumR": -2.484268890447151
      },
      "net": {
        "n": 32,
        "win": 0.46875,
        "meanR": -0.09471738395292074,
        "spt": -0.09608374084849848,
        "sumR": -3.030956286493464
      }
    },
    "short tp2:1": {
      "gross": {
        "n": 31,
        "win": 0.3548387096774194,
        "meanR": 0.02827295867960112,
        "spt": 0.020382027223742882,
        "sumR": 0.8764617190676347
      },
      "net": {
        "n": 31,
        "win": 0.3548387096774194,
        "meanR": 0.011744331154869654,
        "spt": 0.008470443618442833,
        "sumR": 0.36407426580095925
      }
    },
    "long tp1:1": {
      "gross": {
        "n": 58,
        "win": 0.5344827586206896,
        "meanR": 0.08170555295571116,
        "spt": 0.08265077892241343,
        "sumR": 4.738922071431247
      },
      "net": {
        "n": 58,
        "win": 0.5344827586206896,
        "meanR": 0.06356009688837527,
        "spt": 0.0642332262019904,
        "sumR": 3.6864856195257656
      }
    },
    "long tp2:1": {
      "gross": {
        "n": 56,
        "win": 0.35714285714285715,
        "meanR": 0.10231231555181262,
        "spt": 0.07187176905642893,
        "sumR": 5.729489670901507
      },
      "net": {
        "n": 56,
        "win": 0.35714285714285715,
        "meanR": 0.08392443724636489,
        "spt": 0.05896100321765682,
        "sumR": 4.699768485796434
      }
    }
  },
  "BTC-USD daily": {
    "short tp1:1": {
      "gross": {
        "n": 47,
        "win": 0.574468085106383,
        "meanR": 0.1866740928333298,
        "spt": 0.20043335432477016,
        "sumR": 8.7736823631665
      },
      "net": {
        "n": 47,
        "win": 0.574468085106383,
        "meanR": 0.15331591404618317,
        "spt": 0.165032374218349,
        "sumR": 7.205847960170608
      }
    },
    "short tp2:1": {
      "gross": {
        "n": 45,
        "win": 0.4888888888888889,
        "meanR": 0.38909359604224425,
        "spt": 0.2816072035056742,
        "sumR": 17.50921182190099
      },
      "net": {
        "n": 45,
        "win": 0.4888888888888889,
        "meanR": 0.3554457906951572,
        "spt": 0.25731939697223916,
        "sumR": 15.995060581282074
      }
    },
    "long tp1:1": {
      "gross": {
        "n": 81,
        "win": 0.654320987654321,
        "meanR": 0.322346339282078,
        "spt": 0.34603754931289443,
        "sumR": 26.11005348184832
      },
      "net": {
        "n": 81,
        "win": 0.654320987654321,
        "meanR": 0.27732669953760297,
        "spt": 0.30001186662022356,
        "sumR": 22.46346266254584
      }
    },
    "long tp2:1": {
      "gross": {
        "n": 72,
        "win": 0.5694444444444444,
        "meanR": 0.646391104803111,
        "spt": 0.45038884554100256,
        "sumR": 46.54015954582399
      },
      "net": {
        "n": 72,
        "win": 0.5694444444444444,
        "meanR": 0.6005051484040714,
        "spt": 0.42043492322011716,
        "sumR": 43.23637068509314
      }
    },
    "longx2 tp1:1": {
      "gross": {
        "n": 5,
        "win": 0.4,
        "meanR": -0.2,
        "spt": -0.2041241452319315,
        "sumR": -1.0
      },
      "net": {
        "n": 5,
        "win": 0.4,
        "meanR": -0.26577391773091363,
        "spt": -0.2847780996316823,
        "sumR": -1.3288695886545683
      }
    },
    "longx2 tp2:1": {
      "gross": {
        "n": 5,
        "win": 0.4,
        "meanR": 0.2,
        "spt": 0.13608276348795437,
        "sumR": 1.0
      },
      "net": {
        "n": 5,
        "win": 0.4,
        "meanR": 0.13422608226908644,
        "spt": 0.09431737350364523,
        "sumR": 0.6711304113454322
      }
    }
  },
  "EURUSD=X daily": {
    "short tp1:1": {
      "gross": {
        "n": 16,
        "win": 0.375,
        "meanR": -0.25,
        "spt": -0.2581988897471611,
        "sumR": -4.0
      },
      "net": {
        "n": 16,
        "win": 0.375,
        "meanR": -0.2685467889302394,
        "spt": -0.27641703611145074,
        "sumR": -4.296748622883831
      }
    },
    "short tp2:1": {
      "gross": {
        "n": 16,
        "win": 0.25,
        "meanR": -0.2913598422863761,
        "spt": -0.2357786354993591,
        "sumR": -4.661757476582018
      },
      "net": {
        "n": 16,
        "win": 0.25,
        "meanR": -0.30990663121661555,
        "spt": -0.2502547293195306,
        "sumR": -4.958506099465849
      }
    },
    "long tp1:1": {
      "gross": {
        "n": 16,
        "win": 0.6875,
        "meanR": 0.375,
        "spt": 0.40451991747794525,
        "sumR": 6.0
      },
      "net": {
        "n": 16,
        "win": 0.6875,
        "meanR": 0.34944986598568406,
        "spt": 0.3789602043108381,
        "sumR": 5.591197855770945
      }
    },
    "long tp2:1": {
      "gross": {
        "n": 15,
        "win": 0.5333333333333333,
        "meanR": 0.5029367449099549,
        "spt": 0.3470493492770763,
        "sumR": 7.544051173649324
      },
      "net": {
        "n": 15,
        "win": 0.5333333333333333,
        "meanR": 0.4812376696034579,
        "spt": 0.333343182941639,
        "sumR": 7.218565044051868
      }
    }
  },
  "ES=F daily": {
    "short tp1:1": {
      "gross": {
        "n": 27,
        "win": 0.5555555555555556,
        "meanR": 0.13132857628270475,
        "spt": 0.13450305120624842,
        "sumR": 3.545871559633028
      },
      "net": {
        "n": 27,
        "win": 0.5555555555555556,
        "meanR": 0.12896230554034027,
        "spt": 0.13208929781309353,
        "sumR": 3.481982249589187
      }
    },
    "short tp2:1": {
      "gross": {
        "n": 27,
        "win": 0.2962962962962963,
        "meanR": -0.06805967771286284,
        "spt": -0.05360493422948061,
        "sumR": -1.8376112982472965
      },
      "net": {
        "n": 27,
        "win": 0.2962962962962963,
        "meanR": -0.07042594845522732,
        "spt": -0.05547457454107602,
        "sumR": -1.9015006082911374
      }
    },
    "long tp1:1": {
      "gross": {
        "n": 54,
        "win": 0.4444444444444444,
        "meanR": -0.12695085022129046,
        "spt": -0.1291822077273222,
        "sumR": -6.855345911949685
      },
      "net": {
        "n": 54,
        "win": 0.4444444444444444,
        "meanR": -0.13046509095149886,
        "spt": -0.13271607254433582,
        "sumR": -7.045114911380939
      }
    },
    "long tp2:1": {
      "gross": {
        "n": 53,
        "win": 0.37735849056603776,
        "meanR": 0.06177700451047693,
        "spt": 0.04507709418780076,
        "sumR": 3.2741812390552774
      },
      "net": {
        "n": 53,
        "win": 0.37735849056603776,
        "meanR": 0.05824023627628094,
        "spt": 0.04249383297425492,
        "sumR": 3.08673252264289
      }
    }
  },
  "ES 1h": {
    "short tp1:1": {
      "gross": {
        "n": 562,
        "win": 0.45729537366548045,
        "meanR": -0.07275779786923021,
        "spt": -0.07513611189130567,
        "sumR": -40.88988240250738
      },
      "net": {
        "n": 562,
        "win": 0.4555160142348754,
        "meanR": -0.19792021122068665,
        "spt": -0.2018645339486696,
        "sumR": -111.2311587060259
      }
    },
    "short tp2:1": {
      "gross": {
        "n": 554,
        "win": 0.33935018050541516,
        "meanR": -0.03674094041738172,
        "spt": -0.02837605804206003,
        "sumR": -20.354480991229472
      },
      "net": {
        "n": 554,
        "win": 0.33754512635379064,
        "meanR": -0.16206531571061758,
        "spt": -0.12449396078298312,
        "sumR": -89.78418490368215
      }
    },
    "long tp1:1": {
      "gross": {
        "n": 672,
        "win": 0.49255952380952384,
        "meanR": -0.0072713610851905626,
        "spt": -0.007555566442230514,
        "sumR": -4.886354649248058
      },
      "net": {
        "n": 672,
        "win": 0.49255952380952384,
        "meanR": -0.14273042411205927,
        "spt": -0.14642137351786524,
        "sumR": -95.91484500330384
      }
    },
    "long tp2:1": {
      "gross": {
        "n": 655,
        "win": 0.3847328244274809,
        "meanR": 0.029258773826528507,
        "spt": 0.02266419298574456,
        "sumR": 19.16449685637617
      },
      "net": {
        "n": 655,
        "win": 0.383206106870229,
        "meanR": -0.10658605117367416,
        "spt": -0.08224179921225547,
        "sumR": -69.81386351875658
      }
    }
  },
  "NQ 1h": {
    "short tp1:1": {
      "gross": {
        "n": 609,
        "win": 0.46798029556650245,
        "meanR": -0.04336083455797292,
        "spt": -0.04523951513597065,
        "sumR": -26.40674824580551
      },
      "net": {
        "n": 609,
        "win": 0.4663382594417077,
        "meanR": -0.14890292853329246,
        "spt": -0.15362936490929827,
        "sumR": -90.68188347677511
      }
    },
    "short tp2:1": {
      "gross": {
        "n": 600,
        "win": 0.3283333333333333,
        "meanR": -0.0891104290919938,
        "spt": -0.07107094121369222,
        "sumR": -53.466257455196285
      },
      "net": {
        "n": 600,
        "win": 0.325,
        "meanR": -0.19536824225463642,
        "spt": -0.15483716233098926,
        "sumR": -117.22094535278185
      }
    },
    "shortx2 tp1:1": {
      "gross": {
        "n": 6,
        "win": 0.6666666666666666,
        "meanR": 0.3333333333333333,
        "spt": 0.35355339059327373,
        "sumR": 2.0
      },
      "net": {
        "n": 6,
        "win": 0.6666666666666666,
        "meanR": 0.26466667860735626,
        "spt": 0.2851314981258516,
        "sumR": 1.5880000716441376
      }
    },
    "shortx2 tp2:1": {
      "gross": {
        "n": 6,
        "win": 0.6666666666666666,
        "meanR": 0.8154761904761906,
        "spt": 0.6076179710290583,
        "sumR": 4.892857142857143
      },
      "net": {
        "n": 6,
        "win": 0.6666666666666666,
        "meanR": 0.7468095357502135,
        "spt": 0.5609450231685746,
        "sumR": 4.480857214501281
      }
    },
    "long tp1:1": {
      "gross": {
        "n": 752,
        "win": 0.4853723404255319,
        "meanR": -0.033817013275735844,
        "spt": -0.03499820089264815,
        "sumR": -25.430393983353355
      },
      "net": {
        "n": 752,
        "win": 0.48271276595744683,
        "meanR": -0.14963252566501883,
        "spt": -0.15375770778824932,
        "sumR": -112.52365930009417
      }
    },
    "long tp2:1": {
      "gross": {
        "n": 743,
        "win": 0.37415881561238223,
        "meanR": -0.022228046808742883,
        "spt": -0.01737065539281827,
        "sumR": -16.515438778895962
      },
      "net": {
        "n": 743,
        "win": 0.36877523553162855,
        "meanR": -0.13852286317533963,
        "spt": -0.10795876778081916,
        "sumR": -102.92248733927735
      }
    },
    "longx2 tp1:1": {
      "gross": {
        "n": 7,
        "win": 0.5714285714285714,
        "meanR": 0.14285714285714285,
        "spt": 0.14433756729740643,
        "sumR": 1.0
      },
      "net": {
        "n": 7,
        "win": 0.5714285714285714,
        "meanR": 0.039284488738939034,
        "spt": 0.03974682272239261,
        "sumR": 0.27499142117257325
      }
    },
    "longx2 tp2:1": {
      "gross": {
        "n": 7,
        "win": 0.42857142857142855,
        "meanR": 0.02272727272727274,
        "spt": 0.01734257195242087,
        "sumR": 0.15909090909090917
      },
      "net": {
        "n": 7,
        "win": 0.42857142857142855,
        "meanR": -0.08084538139093105,
        "spt": -0.06277160685975844,
        "sumR": -0.5659176697365174
      }
    }
  },
  "ES 15m": {
    "short tp1:1": {
      "gross": {
        "n": 820,
        "win": 0.5182926829268293,
        "meanR": 0.037356471287449095,
        "spt": 0.03784290636010518,
        "sumR": 30.63230645570826
      },
      "net": {
        "n": 820,
        "win": 0.5170731707317073,
        "meanR": -0.12732798075142762,
        "spt": -0.1274195454455001,
        "sumR": -104.40894421617064
      }
    },
    "short tp2:1": {
      "gross": {
        "n": 796,
        "win": 0.35050251256281406,
        "meanR": 0.008369513268330022,
        "spt": 0.0061383249473842515,
        "sumR": 6.662132561590697
      },
      "net": {
        "n": 796,
        "win": 0.3479899497487437,
        "meanR": -0.15698124471267594,
        "spt": -0.11377694265710483,
        "sumR": -124.95707079129005
      }
    },
    "shortx2 tp1:1": {
      "gross": {
        "n": 5,
        "win": 1.0,
        "meanR": 1.0,
        "spt": 0.0,
        "sumR": 5.0
      },
      "net": {
        "n": 5,
        "win": 1.0,
        "meanR": 0.8974118618745139,
        "spt": 31.440801158519392,
        "sumR": 4.48705930937257
      }
    },
    "shortx2 tp2:1": {
      "gross": {
        "n": 5,
        "win": 0.8,
        "meanR": 1.2678571428571428,
        "spt": 1.0906825598176368,
        "sumR": 6.339285714285714
      },
      "net": {
        "n": 5,
        "win": 0.8,
        "meanR": 1.1652690047316567,
        "spt": 1.0026751559289726,
        "sumR": 5.826345023658283
      }
    },
    "long tp1:1": {
      "gross": {
        "n": 839,
        "win": 0.5363528009535161,
        "meanR": 0.06576922773513424,
        "spt": 0.06682715265168625,
        "sumR": 55.18038206977763
      },
      "net": {
        "n": 839,
        "win": 0.5303933253873659,
        "meanR": -0.114024550423947,
        "spt": -0.11467466121035945,
        "sumR": -95.66659780569154
      }
    },
    "long tp2:1": {
      "gross": {
        "n": 818,
        "win": 0.4180929095354523,
        "meanR": 0.13811917964177425,
        "spt": 0.10092185182031099,
        "sumR": 112.98148894697134
      },
      "net": {
        "n": 818,
        "win": 0.41442542787286063,
        "meanR": -0.04221930784238605,
        "spt": -0.03071010753117729,
        "sumR": -34.535393815071785
      }
    }
  },
  "NQ 15m": {
    "short tp1:1": {
      "gross": {
        "n": 839,
        "win": 0.5256257449344458,
        "meanR": 0.051409089423165084,
        "spt": 0.05238948613047971,
        "sumR": 43.132226026035504
      },
      "net": {
        "n": 839,
        "win": 0.5244338498212158,
        "meanR": -0.05861123455630232,
        "spt": -0.059510550380665675,
        "sumR": -49.17482579273765
      }
    },
    "short tp2:1": {
      "gross": {
        "n": 811,
        "win": 0.3723797780517879,
        "meanR": 0.05473666198390667,
        "spt": 0.040088178240672234,
        "sumR": 44.39143286894831
      },
      "net": {
        "n": 811,
        "win": 0.36991368680641185,
        "meanR": -0.05647132945253711,
        "spt": -0.04127898008265054,
        "sumR": -45.7982481860076
      }
    },
    "shortx2 tp1:1": {
      "gross": {
        "n": 11,
        "win": 0.6363636363636364,
        "meanR": 0.2727272727272727,
        "spt": 0.28347335475692037,
        "sumR": 3.0
      },
      "net": {
        "n": 11,
        "win": 0.6363636363636364,
        "meanR": 0.18341196047671585,
        "spt": 0.19133578139077567,
        "sumR": 2.0175315652438743
      }
    },
    "shortx2 tp2:1": {
      "gross": {
        "n": 11,
        "win": 0.45454545454545453,
        "meanR": 0.36363636363636365,
        "spt": 0.24343224778007386,
        "sumR": 4.0
      },
      "net": {
        "n": 11,
        "win": 0.45454545454545453,
        "meanR": 0.27432105138580676,
        "spt": 0.18515248323490252,
        "sumR": 3.0175315652438743
      }
    },
    "long tp1:1": {
      "gross": {
        "n": 916,
        "win": 0.5251091703056768,
        "meanR": 0.04280477261050655,
        "spt": 0.043791334673783704,
        "sumR": 39.209171711224
      },
      "net": {
        "n": 916,
        "win": 0.5240174672489083,
        "meanR": -0.08864650213145184,
        "spt": -0.08989755021084184,
        "sumR": -81.20019595240989
      }
    },
    "long tp2:1": {
      "gross": {
        "n": 899,
        "win": 0.3971078976640712,
        "meanR": 0.07470437652175115,
        "spt": 0.055847931876636066,
        "sumR": 67.15923449305429
      },
      "net": {
        "n": 899,
        "win": 0.39377085650723026,
        "meanR": -0.056505189992008015,
        "spt": -0.04198701399874705,
        "sumR": -50.798165802815205
      }
    },
    "longx2 tp1:1": {
      "gross": {
        "n": 5,
        "win": 0.2,
        "meanR": -0.6,
        "spt": -0.7499999999999999,
        "sumR": -3.0
      },
      "net": {
        "n": 5,
        "win": 0.2,
        "meanR": -0.6943894752777211,
        "spt": -0.8511074620057396,
        "sumR": -3.4719473763886053
      }
    },
    "longx2 tp2:1": {
      "gross": {
        "n": 5,
        "win": 0.0,
        "meanR": -1.0,
        "spt": 0.0,
        "sumR": -5.0
      },
      "net": {
        "n": 5,
        "win": 0.0,
        "meanR": -1.0943894752777212,
        "spt": -22.589328274924956,
        "sumR": -5.471947376388606
      }
    }
  }
}